.coveragerc
.editorconfig
.gitignore
.gitlab-ci.yml
.gitlab-ci.yml.bak
.pre-commit-config.yaml
.zenodo.json
AUTHORS.rst
CITATION
CODE_OF_CONDUCT.rst
CONTRIBUTING.rst
Fernlab_Logo.svg
HISTORY.rst
LICENSE
MANIFEST.in
Makefile
README.rst
environment_enmap_downloader.yml
pyproject.toml
pytest.ini
config/config.json
config/geojson/US-Wi5.geojson
docs/Makefile
docs/authors.rst
docs/conf.py
docs/contributing.rst
docs/enmap_downloader.rst
docs/history.rst
docs/index.html
docs/index.rst
docs/installation.rst
docs/make.bat
docs/modules.rst
docs/readme.rst
docs/_build/html/_static/file.png
docs/_build/html/_static/minus.png
docs/_build/html/_static/plus.png
docs/_static/custom.css
enmap_downloader/__init__.py
enmap_downloader/config.py
enmap_downloader/enmap_downloader.py
enmap_downloader/enmap_downloader_cli.py
enmap_downloader/version.py
enmap_downloader.egg-info/PKG-INFO
enmap_downloader.egg-info/SOURCES.txt
enmap_downloader.egg-info/dependency_links.txt
enmap_downloader.egg-info/not-zip-safe
enmap_downloader.egg-info/requires.txt
enmap_downloader.egg-info/top_level.txt
images/cropping.png
images/eoc_enmap.png
notebooks/US-Wi5.geojson
notebooks/bbox.png
notebooks/cropping.png
notebooks/example_cropped_data.ipynb
notebooks/example_uncropped_data.ipynb