Metadata-Version: 2.4
Name: enmap_downloader
Version: 0.6.4
Summary: Downloader for EnMAP data products with STAC
Author-email:  Global Land Monitoring  <stassin@gfz-potsdam.de>
License: EUPL-1.2
Project-URL: Source code, https://git.gfz-potsdam.de/global-land-monitoring/enmap_downloader
Project-URL: Issue Tracker, https://git.gfz-potsdam.de/global-land-monitoring/enmap_downloader/-/issues
Project-URL: Documentation, https://fernlab.git-pages.gfz-potsdam.de/global-land-monitoring/enmap_downloader/doc/
Project-URL: Change log, https://git.gfz-potsdam.de/global-land-monitoring/enmap_downloader/-/blob/main/HISTORY.rst
Keywords: remote sensing
Classifier: Development Status :: 4 - Beta
Classifier: Intended Audience :: Science/Research
Classifier: Topic :: Scientific/Engineering
Classifier: License :: OSI Approved :: European Union Public Licence 1.2 (EUPL 1.2)
Classifier: Natural Language :: English
Classifier: Programming Language :: Python :: 3.10
Classifier: Programming Language :: Python :: 3.11
Classifier: Programming Language :: Python :: 3.12
License-File: LICENSE
Requires-Dist: requests
Requires-Dist: geojson
Requires-Dist: python-dotenv
Requires-Dist: pystac
Requires-Dist: pystac_client
Requires-Dist: geopandas
Requires-Dist: pydantic
Requires-Dist: gdal
Requires-Dist: rasterio
Requires-Dist: dask
Requires-Dist: tqdm
Requires-Dist: tifffile
Requires-Dist: tenacity
Requires-Dist: docutils==0.20
Provides-Extra: doc
Requires-Dist: sphinx; extra == "doc"
Requires-Dist: sphinx-argparse; extra == "doc"
Requires-Dist: sphinx_rtd_theme; extra == "doc"
Requires-Dist: sphinx-autodoc-typehints; extra == "doc"
Requires-Dist: numpydoc>=1.7; extra == "doc"
Provides-Extra: test
Requires-Dist: pytest>=3; extra == "test"
Requires-Dist: pytest-cov; extra == "test"
Requires-Dist: pytest-reporter-html1==0.9; extra == "test"
Requires-Dist: urlchecker==0.0.34; extra == "test"
Provides-Extra: lint
Requires-Dist: pre-commit; extra == "lint"
Provides-Extra: dev
Requires-Dist: coverage; extra == "dev"
Requires-Dist: pre-commit; extra == "dev"
Requires-Dist: pytest; extra == "dev"
Requires-Dist: twine; extra == "dev"
Requires-Dist: build; extra == "dev"
Dynamic: license-file
